kakaotalk_msg_preprocessor/__init__.py
kakaotalk_msg_preprocessor/kakaotalk_msg_preprocessor.py
kakaotalk_msg_preprocessor-0.13.dist-info/METADATA
kakaotalk_msg_preprocessor-0.13.dist-info/WHEEL
kakaotalk_msg_preprocessor-0.13.dist-info/top_level.txt
kakaotalk_msg_preprocessor-0.13.dist-info/RECORD
