Metadata-Version: 2.1
Name: kakaotalk-msg-preprocessor
Version: 0.13
Summary: Preprocessor for kakaotalk message exported file
Home-page: https://github.com/uoneway/kakaotalk_msg_preprocessor
Author: uoneway
Author-email: uoneway@gmail.com
License: MIT
Keywords: kakaotalk,preprocess,parse,url
Platform: UNKNOWN
Classifier: Programming Language :: Python :: 3.7
Classifier: License :: OSI Approved :: GNU General Public License v3 (GPLv3)
Classifier: Operating System :: OS Independent
Requires-Python: >=3.7
